huaweicloudsdkcdn/__init__.py
huaweicloudsdkcdn/v1/__init__.py
huaweicloudsdkcdn/v1/cdn_async_client.py
huaweicloudsdkcdn/v1/cdn_client.py
huaweicloudsdkcdn/v1/model/__init__.py
huaweicloudsdkcdn/v1/model/back_sources.py
huaweicloudsdkcdn/v1/model/batch_delete_tags_request.py
huaweicloudsdkcdn/v1/model/batch_delete_tags_response.py
huaweicloudsdkcdn/v1/model/black_white_list_body.py
huaweicloudsdkcdn/v1/model/cache_config.py
huaweicloudsdkcdn/v1/model/cache_config_request.py
huaweicloudsdkcdn/v1/model/cache_config_request_body.py
huaweicloudsdkcdn/v1/model/cache_rules.py
huaweicloudsdkcdn/v1/model/cache_url_parameter_filter.py
huaweicloudsdkcdn/v1/model/cdn_ips.py
huaweicloudsdkcdn/v1/model/common_remote_auth.py
huaweicloudsdkcdn/v1/model/compress.py
huaweicloudsdkcdn/v1/model/compress_request.py
huaweicloudsdkcdn/v1/model/compress_response.py
huaweicloudsdkcdn/v1/model/compress_rules.py
huaweicloudsdkcdn/v1/model/configs.py
huaweicloudsdkcdn/v1/model/configs_get_body.py
huaweicloudsdkcdn/v1/model/create_domain_request.py
huaweicloudsdkcdn/v1/model/create_domain_request_body.py
huaweicloudsdkcdn/v1/model/create_domain_response.py
huaweicloudsdkcdn/v1/model/create_domain_response_body_content.py
huaweicloudsdkcdn/v1/model/create_preheating_tasks_request.py
huaweicloudsdkcdn/v1/model/create_preheating_tasks_response.py
huaweicloudsdkcdn/v1/model/create_refresh_tasks_request.py
huaweicloudsdkcdn/v1/model/create_refresh_tasks_response.py
huaweicloudsdkcdn/v1/model/create_tags_request.py
huaweicloudsdkcdn/v1/model/create_tags_request_body.py
huaweicloudsdkcdn/v1/model/create_tags_response.py
huaweicloudsdkcdn/v1/model/custom_args.py
huaweicloudsdkcdn/v1/model/delete_domain_request.py
huaweicloudsdkcdn/v1/model/delete_domain_response.py
huaweicloudsdkcdn/v1/model/delete_tags_request_body.py
huaweicloudsdkcdn/v1/model/disable_domain_request.py
huaweicloudsdkcdn/v1/model/disable_domain_response.py
huaweicloudsdkcdn/v1/model/domain_body.py
huaweicloudsdkcdn-3.1.184.dist-info/METADATA
huaweicloudsdkcdn-3.1.184.dist-info/WHEEL
huaweicloudsdkcdn-3.1.184.dist-info/licenses/LICENSE
huaweicloudsdkcdn-3.1.184.dist-info/RECORD
